LICENSE
MANIFEST.in
README.md
requirements.txt
setup.py
Deep_Tumour_Spheroid.egg-info/PKG-INFO
Deep_Tumour_Spheroid.egg-info/SOURCES.txt
Deep_Tumour_Spheroid.egg-info/dependency_links.txt
Deep_Tumour_Spheroid.egg-info/entry_points.txt
Deep_Tumour_Spheroid.egg-info/requires.txt
Deep_Tumour_Spheroid.egg-info/top_level.txt
deep_tumour_spheroid/__init__.py
deep_tumour_spheroid/biomedical_image_utils.py
deep_tumour_spheroid/cli.py
deep_tumour_spheroid/gui.py
deep_tumour_spheroid/predict.py