Metadata-Version: 2.1
Name: Deep-Tumour-Spheroid
Version: 1.0.0rc1
Summary: Deep Learning methods for the segmentation of Tumour Spheroids
Home-page: https://github.com/WaterKnight1998/Deep-Tumour-Spheroid
Author: David Lacalle Castillo
Author-email: dvdlacallecastillo@gmail.com
Maintainer: David Lacalle Castillo
Maintainer-email: dvdlacallecastillo@gmail.com
License: GNU General Public License v3 (GPLv3)
Keywords: gbm brain tumour spheroid spheroids deep learning semantic segmentation pytorch
Platform: UNKNOWN
Classifier: Development Status :: 5 - Production/Stable
Classifier: Intended Audience :: Science/Research
Classifier: Intended Audience :: Healthcare Industry
Classifier: Intended Audience :: Developers
Classifier: Topic :: Scientific/Engineering :: Bio-Informatics
Classifier: Topic :: Scientific/Engineering :: Medical Science Apps.
Classifier: Topic :: Scientific/Engineering :: Image Recognition
Classifier: Topic :: Scientific/Engineering :: Artificial Intelligence
Classifier: License :: OSI Approved :: GNU General Public License v3 (GPLv3)
Classifier: Programming Language :: Python :: 3.6
Classifier: Programming Language :: Python :: 3.7
Classifier: Programming Language :: Python :: 3.8
